titans/__init__.py
titans/models/__init__.py
titans/models/titans_base.py
titans/models/titans_mac.py
titans/models/titans_mag.py
titans/models/titans_mal.py
titans/utils/__init__.py
titans/utils/attention.py
titans/utils/memory.py
titans/utils/persistent_memory.py
titans_unofficial-1.1.0.dist-info/LICENSE
titans_unofficial-1.1.0.dist-info/METADATA
titans_unofficial-1.1.0.dist-info/WHEEL
titans_unofficial-1.1.0.dist-info/top_level.txt
titans_unofficial-1.1.0.dist-info/RECORD
